sp_algopyformancelib/__init__.py
sp_algopyformancelib/tests.py
sp_algopyformance-0.1.2.dist-info/METADATA
sp_algopyformance-0.1.2.dist-info/WHEEL
sp_algopyformance-0.1.2.dist-info/top_level.txt
sp_algopyformance-0.1.2.dist-info/RECORD
