Metadata-Version: 2.1
Name: sp-algopyformance
Version: 0.1.2
Summary: A package to aid students of ISCTE in testing their algorithms
Home-page: https://github.com/stefanpostolache/algopyformance
Author: Stefan Postolache
Author-email: stefanogiovanochestii@gmail.com
License: MIT
Platform: UNKNOWN
Classifier: Programming Language :: Python :: 3
Classifier: License :: OSI Approved :: MIT License
Classifier: Operating System :: OS Independent
Requires-Dist: Pillow
Requires-Dist: cycler
Requires-Dist: matplotlib
Requires-Dist: seaborn
Requires-Dist: pandas
Requires-Dist: numpy
Requires-Dist: typing
Requires-Dist: typing-extensions
Requires-Dist: fonttools
Requires-Dist: kiwisolver
Requires-Dist: packaging
Requires-Dist: pyparsing
Requires-Dist: python-dateutil
Requires-Dist: pytz
Requires-Dist: scipy
Requires-Dist: six
